tom_eso/__init__.py
tom_eso/admin.py
tom_eso/apps.py
tom_eso/eso.py
tom_eso/eso_api.py
tom_eso/forms.py
tom_eso/migrations/0001_initial.py
tom_eso/migrations/0002_alter_esoprofile_p2_environment_and_more.py
tom_eso/migrations/0003_alter_esoprofile_p2_username.py
tom_eso/migrations/__init__.py
tom_eso/models.py
tom_eso/templates/tom_eso/eso_update_user_profile.html
tom_eso/templates/tom_eso/observation_form.html
tom_eso/templates/tom_eso/partials/eso_user_profile.html
tom_eso/templatetags/eso_extras.py
tom_eso/tests/boot_django.py
tom_eso/tests/check_migrations.py
tom_eso/tests/django_shell.py
tom_eso/tests/run_tests.py
tom_eso/tests/tests.py
tom_eso/urls.py
tom_eso/views.py
tom_eso-0.2.2.dist-info/METADATA
tom_eso-0.2.2.dist-info/WHEEL
tom_eso-0.2.2.dist-info/licenses/LICENSE
tom_eso-0.2.2.dist-info/RECORD
