Metadata-Version: 2.4
Name: tom-eso
Version: 0.2.2
Summary: TOM Toolkit Facility module for the European Southern Observatory telescopes
License-Expression: GPL-3.0-or-later
License-File: LICENSE
Author: Lindy Lindstrom
Author-email: llindstrom@lco.global
Requires-Python: >=3.10,<3.13
Classifier: Programming Language :: Python :: 3
Classifier: Programming Language :: Python :: 3.10
Classifier: Programming Language :: Python :: 3.11
Classifier: Programming Language :: Python :: 3.12
Requires-Dist: p2api (>=1,<2)
Requires-Dist: phase1api (>=0,<2)
Requires-Dist: tomtoolkit (>=2.29.0,<3)
